wrapvenv/__init__.py
wrapvenv/__main__.py
wrapvenv-1.2.1.dist-info/METADATA
wrapvenv-1.2.1.dist-info/WHEEL
wrapvenv-1.2.1.dist-info/entry_points.txt
wrapvenv-1.2.1.dist-info/licenses/LICENSE
wrapvenv-1.2.1.dist-info/RECORD
