Metadata-Version: 2.4
Name: wrapvenv
Version: 1.2.1
Summary: Yet another python virtual environments manager
Project-URL: Homepage, https://git.sr.ht/~greenfoo/wrapvenv
Project-URL: Issues, https://todo.sr.ht/~greenfoo/wrapvenv
License-File: LICENSE
Classifier: Operating System :: OS Independent
Classifier: Programming Language :: Python :: 3
Requires-Python: >=3.7
